boggle/__init__.py
boggle/board.py
boggle-0.1.2.dist-info/entry_points.txt
boggle-0.1.2.dist-info/LICENSE
boggle-0.1.2.dist-info/WHEEL
boggle-0.1.2.dist-info/METADATA
boggle-0.1.2.dist-info/RECORD
