Metadata-Version: 2.1
Name: boggle
Version: 0.1.2
Summary: Generate boards for the game boggle
Home-page: https://gitlab.com/bmaximuml-os/boggle
License: GPL-3.0-or-later
Keywords: boggle,game,board game,word game
Author: Max Levine
Author-email: max@maxlevine.co.uk
Requires-Python: >=3.7,<4.0
Classifier: License :: OSI Approved :: GNU General Public License v3 or later (GPLv3+)
Classifier: Programming Language :: Python :: 3
Classifier: Programming Language :: Python :: 3.10
Classifier: Programming Language :: Python :: 3.7
Classifier: Programming Language :: Python :: 3.8
Classifier: Programming Language :: Python :: 3.9
Requires-Dist: click (>=8.1.3,<9.0.0)
Requires-Dist: tabulate (>=0.8.10,<0.9.0)
Project-URL: Documentation, https://gitlab.com/bmaximuml-os/boggle
